datagate/__init__.py
datagate-0.0.0.dist-info/METADATA
datagate-0.0.0.dist-info/WHEEL
datagate-0.0.0.dist-info/top_level.txt
datagate-0.0.0.dist-info/RECORD
